optimizador_joshua_2/__init__.py
optimizador_joshua_2/baseopt.py
optimizador_joshua_2/funciones/__init__.py
optimizador_joshua_2/funciones/base.py
optimizador_joshua_2/funciones/objetivo.py
optimizador_joshua_2/funciones/restriccion.py
optimizador_joshua_2/funciones/univariablef.py
optimizador_joshua_2/metodos_multivariables/__init__.py
optimizador_joshua_2/metodos_multivariables/cauchy.py
optimizador_joshua_2/metodos_multivariables/fletcherreeves.py
optimizador_joshua_2/metodos_multivariables/hookejeeves.py
optimizador_joshua_2/metodos_multivariables/neldermead.py
optimizador_joshua_2/metodos_multivariables/newtonmethod.py
optimizador_joshua_2/metodos_multivariables/randomwalk.py
optimizador_joshua_2/metodos_univariables/__init__.py
optimizador_joshua_2/metodos_univariables/biseccion.py
optimizador_joshua_2/metodos_univariables/fibonacci.py
optimizador_joshua_2/metodos_univariables/golden.py
optimizador_joshua_2/metodos_univariables/interval.py
optimizador_joshua_2/metodos_univariables/newtonraphson.py
optimizador_joshua_2/metodos_univariables/secante.py
optimizador_joshua_2-0.1.dist-info/METADATA
optimizador_joshua_2-0.1.dist-info/WHEEL
optimizador_joshua_2-0.1.dist-info/top_level.txt
optimizador_joshua_2-0.1.dist-info/RECORD
